fastidious2/__init__.py
fastidious2/cli.py
fastidious2/expression.py
fastidious2/fastidious2.py
fastidious2/reader.py
fastidious2/ast/__init__.py
fastidious2/ast/field.py
fastidious2/ast/sexpr.py
fastidious2/ast/utils.py
fastidious2/ast/visitor.py
fastidious2/compiler/__init__.py
fastidious2/compiler/compile_actions.py
fastidious2/grammar/__init__.py
fastidious2/grammar/peg/__init__.py
fastidious2/grammar/peg/bootstrap.py
fastidious2/grammar/peg/tests/__init__.py
fastidious2/grammar/peg/tests/test_bootstrap.py
fastidious2-0.1.1.dist-info/AUTHORS.rst
fastidious2-0.1.1.dist-info/LICENSE
fastidious2-0.1.1.dist-info/METADATA
fastidious2-0.1.1.dist-info/WHEEL
fastidious2-0.1.1.dist-info/entry_points.txt
fastidious2-0.1.1.dist-info/top_level.txt
fastidious2-0.1.1.dist-info/RECORD
