Metadata-Version: 2.1
Name: fastidious2
Version: 0.1.1
Summary: The best PEG parser generator I write (so far)
Home-page: https://gitlab.com/lisael/fastidious2
Author: Bruno Dupuis
Author-email: bdupuis@lisael.org
License: GNU General Public License v3
Keywords: fastidious2
Platform: UNKNOWN
Classifier: Development Status :: 2 - Pre-Alpha
Classifier: Intended Audience :: Developers
Classifier: License :: OSI Approved :: GNU General Public License v3 (GPLv3)
Classifier: Natural Language :: English
Classifier: Programming Language :: Python :: 3
Classifier: Programming Language :: Python :: 3.5
Classifier: Programming Language :: Python :: 3.6
Classifier: Programming Language :: Python :: 3.7
Classifier: Programming Language :: Python :: 3.8
Requires-Python: >=3.5
